agent/__init__.py
agent/agent.py
agent/chat.py
agent/chat_console.py
agent/default_agent.py
agent/prompt_agent.py
agent/retrieve_agent.py
agent/chat/__init__.py
agent/chat/common.py
agent/chat/streamlit_chat.py
agent/chat/terminal_chat.py
agent/interface/__init__.py
agent/interface/agent.py
agent/interface/chat.py
client/__init__.py
client/aws_bedrock.py
client/config.py
client/groq_client.py
client/openai_client.py
dspyagent/__init__.py
dspyagent/agent.py
dspyagent/chat.py
dspyagent/interface.py
memory/__init__.py
memory/chat_buffer_memory.py
memory/chat_buffered_memory.py
memory/chat_memory.py
memory/chat_vector_memory.py
tool/__init__.py
tool/code_executor.py
tool/kubectl_executor.py
tool/metadata.py
tool/online_tool.py
tool/serper.py
type/__init__.py
type/action_permission.py
type/chat_client.py
type/chat_message.py
type/status_code.py
agent_chat-0.1.1.dist-info/METADATA
agent_chat-0.1.1.dist-info/WHEEL
agent_chat-0.1.1.dist-info/top_level.txt
agent_chat-0.1.1.dist-info/RECORD
