Metadata-Version: 2.1
Name: agent-chat
Version: 0.1.1
Summary: AgentChat facilitates the creation of AI assistant and the development of advanced multi-agent system.
Home-page: https://github.com/yanmxa/chat-agent
Author: Meng Yan
Author-email: yanmxa@gmail.com
Requires-Dist: boto3
